{
    "currentPage": 1319,
    "pageSize": 5,
    "items": [
        {
            "videoId": "urhIQQYjNAo",
            "title": "Swamp People: Isaac on the Way | History",
            "secondDuration": 191,
            "group": "group_12"
        },
        {
            "videoId": "zPAwXlpo87M",
            "title": "Top Shot - Top Shot All-Stars Image Spot | History",
            "secondDuration": 31,
            "group": "group_12"
        },
        {
            "videoId": "xo_n9HyRSzE",
            "title": "Counting Cars - Typical Day in the Shop | History",
            "secondDuration": 131,
            "group": "group_12"
        },
        {
            "videoId": "1bd-yFtrDHs",
            "title": "Top Shot - Redemption | History",
            "secondDuration": 122,
            "group": "group_12"
        },
        {
            "videoId": "RvDTp8DUX1I",
            "title": "Only In America with Larry the Cable Guy - Toilet Table | History",
            "secondDuration": 176,
            "group": "group_12"
        }
    ],
    "nbPages": 1444,
    "nbResults": 7217
}