{
    "currentPage": 87,
    "pageSize": 5,
    "items": [
        {
            "videoId": "o6XwTs2Qfeg",
            "title": "Vytas SunSpiral: Refactoring Space Exploration with Soft Machines",
            "secondDuration": 3553,
            "group": "group_8"
        },
        {
            "videoId": "RJVL80Gg3lA",
            "title": "Visualizing Data Using t-SNE",
            "secondDuration": 3310,
            "group": "group_8"
        },
        {
            "videoId": "hCvbNAD8tfc",
            "title": "Google NYC Tech Talks: Crisis Response @ Google",
            "secondDuration": 5673,
            "group": "group_8"
        },
        {
            "videoId": "IGavGSOSAoM",
            "title": "Google NYC Tech Talk: Breaking the Matrix - Android Testing at Scale",
            "secondDuration": 2791,
            "group": "group_8"
        },
        {
            "videoId": "jJ-IwnnjBy0",
            "title": "PhDs at Google: The Embedded Approach to Research",
            "secondDuration": 4895,
            "group": "group_8"
        }
    ],
    "nbPages": 444,
    "nbResults": 2220
}