{
    "currentPage": 11132,
    "pageSize": 5,
    "items": [
        {
            "videoId": "rKvr3HmaBXI",
            "title": "Social Media's Impact on 2012 Presidential Election : 'This Week' Panel Discussion",
            "secondDuration": 219,
            "group": "group_7"
        },
        {
            "videoId": "xmCPf8l_4-U",
            "title": "Do Presidential Debates Change Elections? : 'This Week' Panel Discussion",
            "secondDuration": 1189,
            "group": "group_7"
        },
        {
            "videoId": "nYbSp_SuoRE",
            "title": "Sen. Rob Portman 'This Week' Interview: Mitt Romney Prepares For 2nd Debate Vs. President Obama",
            "secondDuration": 535,
            "group": "group_7"
        },
        {
            "videoId": "DIGfSFFYzyo",
            "title": "Beau Biden 'This Week' Interview: 'Defending my Dad' Joe Biden Against Debate Criticism",
            "secondDuration": 285,
            "group": "group_7"
        },
        {
            "videoId": "-Vx3uqz7nXU",
            "title": "2012 Presidential Debate Format, Role of Moderator: 'This Week' Panel Discussion",
            "secondDuration": 226,
            "group": "group_7"
        }
    ],
    "nbPages": 13408,
    "nbResults": 67038
}