{
    "currentPage": 2638,
    "pageSize": 5,
    "items": [
        {
            "videoId": "1kq1BV3Coxk",
            "title": "20/20 | American Catastrophe | PART 2",
            "secondDuration": 450,
            "group": "group_7"
        },
        {
            "videoId": "bF96I3hNsNk",
            "title": "20/20 | American Catastrophe | PART 3",
            "secondDuration": 455,
            "group": "group_7"
        },
        {
            "videoId": "mxDX4S8IsJc",
            "title": "What happened when former federal officials sounded the alarm on COVID-19: Nightline",
            "secondDuration": 634,
            "group": "group_7"
        },
        {
            "videoId": "pPQMLbRjsic",
            "title": "Sen. Duckworth: Unemployed Americans ‘need this money’",
            "secondDuration": 475,
            "group": "group_7"
        },
        {
            "videoId": "uGH_lshMyMs",
            "title": "Captain America’s political pursuit",
            "secondDuration": 448,
            "group": "group_7"
        }
    ],
    "nbPages": 13408,
    "nbResults": 67037
}