{
    "currentPage": 4892,
    "pageSize": 5,
    "items": [
        {
            "videoId": "sxKeN3edJYM",
            "title": "NBA player files civil rights lawsuit over stun-gun arrest",
            "secondDuration": 166,
            "group": "group_7"
        },
        {
            "videoId": "n6Vk3yCvnB0",
            "title": "US immigration and child separation policy continues to spark backlash",
            "secondDuration": 506,
            "group": "group_7"
        },
        {
            "videoId": "ScRpcNcR0SY",
            "title": "Behind the scenes with the directors of the hit new Ruth Bader Ginsburg doc 'RBG'",
            "secondDuration": 431,
            "group": "group_7"
        },
        {
            "videoId": "RESoJ4Aunx4",
            "title": "Crisis at the border",
            "secondDuration": 258,
            "group": "group_7"
        },
        {
            "videoId": "E2_A1SL_7to",
            "title": "NBA player Sterling Brown files federal civil rights lawsuit over stun-gun arrest",
            "secondDuration": 110,
            "group": "group_7"
        }
    ],
    "nbPages": 13408,
    "nbResults": 67038
}