{
    "currentPage": 477,
    "pageSize": 10,
    "items": [
        {
            "videoId": "V3-JwGydSHs",
            "title": "Azio KB337BP Wireless Media Keyboard With Touchpad Unboxing  & First Look Linus Tech Tips",
            "secondDuration": 379,
            "group": "group_8"
        },
        {
            "videoId": "QUkvhOhrDVk",
            "title": "Intel vs AMD Gaming CPU Showdown 2500K vs 1100T with Quad SLI Linus Tech Tips",
            "secondDuration": 478,
            "group": "group_8"
        },
        {
            "videoId": "lWvAslQJ9XY",
            "title": "890FX vs 990FX Chipset With 1100T CPU Gaming Performance Comparison Linus Tech Tips",
            "secondDuration": 474,
            "group": "group_8"
        },
        {
            "videoId": "yQpfgiQd7WU",
            "title": "AMD A8-3850 vs Phenom II X6 1100T With Radeon 6990 Linus Tech Tips",
            "secondDuration": 360,
            "group": "group_8"
        },
        {
            "videoId": "LxlQLzOCxEc",
            "title": "AMD A8-3850 APU Gaming Performance Comparison Linus Tech Tips",
            "secondDuration": 638,
            "group": "group_8"
        },
        {
            "videoId": "kDXVRLj1SYo",
            "title": "ASUS Matrix GeForce GTX 580 Unboxing & First Look Linus Tech Tips",
            "secondDuration": 507,
            "group": "group_8"
        },
        {
            "videoId": "F4dcby2sww0",
            "title": "MSI A75MA-G55 A75 FM1 APU Fusion Motherboard Unboxing & First Look Linus Tech Tips",
            "secondDuration": 369,
            "group": "group_8"
        },
        {
            "videoId": "s0z8M90YMJk",
            "title": "ASUS Crosshair V Formula 990FX SLI Crossfire Motherboard Unboxing & First Look Linus Tech Tips",
            "secondDuration": 536,
            "group": "group_8"
        },
        {
            "videoId": "AODLzcfA7U4",
            "title": "Patriot Wildfire Extreme Speed SATA3 SSD Unboxing & First Look Linus Tech Tips",
            "secondDuration": 362,
            "group": "group_8"
        },
        {
            "videoId": "iSyj0f9u2z4",
            "title": "Intel Core i3 2105 Sandy Bridge CPU Unboxing & First Look Linus Tech Tips",
            "secondDuration": 224,
            "group": "group_8"
        }
    ],
    "nbPages": 568,
    "nbResults": 5672
}