{
    "currentPage": 4942,
    "pageSize": 10,
    "items": [
        {
            "videoId": "Qi90iAudqxI",
            "title": "Using sex to get ahead in DC: Does it work?",
            "secondDuration": 188,
            "group": "group_7"
        },
        {
            "videoId": "29mBiwCvgMg",
            "title": "BPA: Risking our kids health?",
            "secondDuration": 98,
            "group": "group_7"
        },
        {
            "videoId": "Gp6ISnqxK9w",
            "title": "Sequester threatens program for women and children",
            "secondDuration": 205,
            "group": "group_7"
        },
        {
            "videoId": "OHD6rfqye5A",
            "title": "Obama defends stance against Prop 8",
            "secondDuration": 161,
            "group": "group_7"
        },
        {
            "videoId": "_uYRtU-tBvM",
            "title": "Obama: Sequester pain \"will be real\"",
            "secondDuration": 402,
            "group": "group_7"
        },
        {
            "videoId": "WUZZ9dm7KNw",
            "title": "Preview: Aaron Neville on when he discovered his voice",
            "secondDuration": 70,
            "group": "group_7"
        },
        {
            "videoId": "GSDVFvRcJkQ",
            "title": "Obama: Deficit fight cannot obscure focus on other issues",
            "secondDuration": 117,
            "group": "group_7"
        },
        {
            "videoId": "4_igFwtSmJg",
            "title": "Obama: \"We will get through\" the \"dumb\" sequester",
            "secondDuration": 57,
            "group": "group_7"
        },
        {
            "videoId": "PKzb88XAvFo",
            "title": "Obama: Some Republicans \"paint horns on my head\"",
            "secondDuration": 109,
            "group": "group_7"
        },
        {
            "videoId": "RaFItozGfRk",
            "title": "Preview: The Life and Death of Clay Hunt",
            "secondDuration": 78,
            "group": "group_7"
        }
    ],
    "nbPages": 8454,
    "nbResults": 84536
}