{
    "currentPage": 4855,
    "pageSize": 5,
    "items": [
        {
            "videoId": "uH3hE3LPi2s",
            "title": "Madonna Makes Out With Drake At Coachella",
            "secondDuration": 310,
            "group": "group_7"
        },
        {
            "videoId": "fW16ohQkNGI",
            "title": "Ex-NFL Darren Sharper To Wear Penis Monitor During Probation",
            "secondDuration": 458,
            "group": "group_7"
        },
        {
            "videoId": "9sJh-Ieats4",
            "title": "Social Media Outraged By Gwyneth Paltrow’s Food Stamp Challenge",
            "secondDuration": 340,
            "group": "group_7"
        },
        {
            "videoId": "WdVYm0PHWOc",
            "title": "Officer Slager Laughs About Adrenaline Rush After Walter Scott Shooting",
            "secondDuration": 362,
            "group": "group_7"
        },
        {
            "videoId": "hjMpiUDE0ck",
            "title": "65-Year-Old Woman Is Pregnant With Quadruplets In Berlin",
            "secondDuration": 265,
            "group": "group_7"
        }
    ],
    "nbPages": 5458,
    "nbResults": 27290
}