{
    "currentPage": 5188,
    "pageSize": 5,
    "items": [
        {
            "videoId": "q8S32BVsQ-U",
            "title": "Il Gabinetto delle meraviglie. | Arianna Porcelli Safonov | TEDxFoggia",
            "secondDuration": 1084,
            "group": "group_14"
        },
        {
            "videoId": "FhfWmT9N6Og",
            "title": "Chart-Topping Singer Monique DeBose Performs at TEDx | Monique DeBose | TEDxIVC",
            "secondDuration": 584,
            "group": "group_14"
        },
        {
            "videoId": "z_aRRRBSw7I",
            "title": "Lo Spazio come laboratorio del possibile. | Domenico Maria Caprioli | TEDxFoggia",
            "secondDuration": 869,
            "group": "group_14"
        },
        {
            "videoId": "0Zna_-2JBSQ",
            "title": "La Terra: una meraviglia da proteggere. | Potito Ruggiero | TEDxFoggia",
            "secondDuration": 595,
            "group": "group_14"
        },
        {
            "videoId": "0T1anN-htKI",
            "title": "Le dimensioni non contano. | Alessandro Russo | TEDxFoggia",
            "secondDuration": 1242,
            "group": "group_14"
        }
    ],
    "nbPages": 6927,
    "nbResults": 34631
}