{
    "currentPage": 268,
    "pageSize": 10,
    "items": [
        {
            "videoId": "H2hOwKszKRo",
            "title": "Controlling a plane in space",
            "secondDuration": 640,
            "group": "group_14"
        },
        {
            "videoId": "QL6qb1h65hg",
            "title": "Computing a tangent plane",
            "secondDuration": 581,
            "group": "group_14"
        },
        {
            "videoId": "-82UNytyrCQ",
            "title": "Circuit Terminology",
            "secondDuration": 483,
            "group": "group_14"
        },
        {
            "videoId": "xRGjQdHToNA",
            "title": "Apostrophes and plurals | The Apostrophe | Punctuation | Khan Academy",
            "secondDuration": 171,
            "group": "group_14"
        },
        {
            "videoId": "Yhaa214UKvA",
            "title": "Choosing between its and it’s | The Apostrophe | Punctuation | Khan Academy",
            "secondDuration": 151,
            "group": "group_14"
        },
        {
            "videoId": "BjIPqJ0paXI",
            "title": "BONUS: History of the possessive apostrophe | The Apostrophe | Punctuation | Khan Academy",
            "secondDuration": 657,
            "group": "group_14"
        },
        {
            "videoId": "u-FSLjbuv_s",
            "title": "BONUS: History of the apostrophe | The Apostrophe | Punctuation | Khan Academy",
            "secondDuration": 340,
            "group": "group_14"
        },
        {
            "videoId": "2M4EDrD3aBQ",
            "title": "Introduction to the possessive | The Apostrophe | Punctuation | Khan Academy",
            "secondDuration": 225,
            "group": "group_14"
        },
        {
            "videoId": "_GiPxFvUUxs",
            "title": "Possession for words ending in “s” | The Apostrophe | Punctuation | Khan Academy",
            "secondDuration": 111,
            "group": "group_14"
        },
        {
            "videoId": "2M9cVwj3AtI",
            "title": "Advanced (plural) possession | The Apostrophe | Punctuation | Khan Academy",
            "secondDuration": 251,
            "group": "group_14"
        }
    ],
    "nbPages": 828,
    "nbResults": 8277
}