{
    "currentPage": 3,
    "pageSize": 10,
    "items": [
        {
            "videoId": "KYM05WIkbHI",
            "title": "Big Loz Reveals Who Eddie Injured + Lou Ferrigno Launches NFT Bodybuilding Museum + Nick Vs Hunter",
            "secondDuration": 649,
            "group": "group_15"
        },
        {
            "videoId": "_MOuWoxIQrg",
            "title": "Eddie VS Thor Confrontation was a Set Up + Regan Grimes Done Competing + Urs Kalecinski to Kuwait",
            "secondDuration": 712,
            "group": "group_15"
        },
        {
            "videoId": "kNGJw9mzNBw",
            "title": "Hafthor Says Eddie Hall \"Severely Injured Someone\" After Their Confrontation in Dubai...",
            "secondDuration": 384,
            "group": "group_15"
        },
        {
            "videoId": "bJb4gUDyzOY",
            "title": "Eddie VS Thor My Pick to Win...",
            "secondDuration": 586,
            "group": "group_15"
        },
        {
            "videoId": "rgdaRFkQ9xA",
            "title": "Why I removed the Eddie Vs Thor Confrontation Clip...",
            "secondDuration": 157,
            "group": "group_15"
        },
        {
            "videoId": "HSCw_Xn5b94",
            "title": "William Bonac Addresses Gyno and Midsection Issues in His Emotional Victory Speech",
            "secondDuration": 369,
            "group": "group_15"
        },
        {
            "videoId": "_IGZra273RU",
            "title": "Eddie and Thor First Confrontation Footage + Urs Kalecinski Dominates Boston + Scorecard Review",
            "secondDuration": 534,
            "group": "group_15"
        },
        {
            "videoId": "xoRoQwm0Anw",
            "title": "2022 Boston Pro Finals and Recap",
            "secondDuration": 522,
            "group": "group_15"
        },
        {
            "videoId": "mmL7LEgYATs",
            "title": "Boston Pro Prejudging Top 4 First Callout",
            "secondDuration": 244,
            "group": "group_15"
        },
        {
            "videoId": "ATmeTKfSZWg",
            "title": "Judge Explains Why Bonac Lost Arnold + Eddie VS Thor Canceled AGAIN?? + Blessing Awodibu 8 Weeks Out",
            "secondDuration": 568,
            "group": "group_15"
        }
    ],
    "nbPages": 249,
    "nbResults": 2483
}