{
    "currentPage": 285,
    "pageSize": 5,
    "items": [
        {
            "videoId": "28lxCkthllA",
            "title": "Langmaster - Từ vựng tiếng Anh chủ đề Công Viên & Sân Chơi [Học tiếng Anh cho người mới bắt đầu #1]",
            "secondDuration": 420,
            "group": "group_1"
        },
        {
            "videoId": "kBiQ4kLkaL4",
            "title": "Langmaster - Những lời tri ân thầy cô ngày 20-11 ý nghĩa nhất [Học tiếng Anh cho người mất gốc #1]",
            "secondDuration": 666,
            "group": "group_1"
        },
        {
            "videoId": "eIXgTnlyAro",
            "title": "Langmaster - Ngày đầu tiên đi làm nói gì cho CHẤT? - Khóa học tiếng Anh giao tiếp cho người đi làm",
            "secondDuration": 614,
            "group": "group_1"
        },
        {
            "videoId": "rXbRjr73rbc",
            "title": "Langmaster - Dùng GIỚI TỪ CHỈ ĐỊA ĐIỂM như thế nào? (phần 2) [Học tiếng Anh giao tiếp cơ bản]",
            "secondDuration": 452,
            "group": "group_1"
        },
        {
            "videoId": "SimGlypvOWE",
            "title": "Langmaster - TẤT TẦN TẬT tính từ miêu tả NGOẠI HÌNH của chúng ta [Học tiếng Anh giao tiếp cơ bản]",
            "secondDuration": 486,
            "group": "group_1"
        }
    ],
    "nbPages": 558,
    "nbResults": 2790
}