{
    "currentPage": 90,
    "pageSize": 5,
    "items": [
        {
            "videoId": "F-7tTmFIvqo",
            "title": "90 min Yin Yoga Full Class - Deep Stretches & Long Holds",
            "secondDuration": 5086,
            "group": "group_13"
        },
        {
            "videoId": "RTYl7g2DHtE",
            "title": "10 min Neck Stretches to Reduce Pain & Stiffness",
            "secondDuration": 623,
            "group": "group_13"
        },
        {
            "videoId": "7-2GShJtR50",
            "title": "15 min Obliques Side Abs Workout - At Home No Equipment",
            "secondDuration": 930,
            "group": "group_13"
        },
        {
            "videoId": "gFX__Db_Wj4",
            "title": "Simple & Minimalist Morning Routine For A Positive Productive Day",
            "secondDuration": 753,
            "group": "group_13"
        },
        {
            "videoId": "Oz-JafPSUAY",
            "title": "Twist and Energize Yoga Detox - 30 min Vinyasa Flow",
            "secondDuration": 1636,
            "group": "group_13"
        }
    ],
    "nbPages": 130,
    "nbResults": 646
}