{
    "currentPage": 831,
    "pageSize": 10,
    "items": [
        {
            "videoId": "w5JzBNML2J0",
            "title": "Mark Ruffalo apologizes for 'inflammatory' posts on Israel-Hamas conflict",
            "secondDuration": 420,
            "group": "group_7"
        },
        {
            "videoId": "Rj0poKP0YRs",
            "title": "Will Cain: Terrifying how much Chinese dollars control American speech",
            "secondDuration": 411,
            "group": "group_7"
        },
        {
            "videoId": "ylLf2o5mSR4",
            "title": "Biden administration shut down COVID lab-leak investigation: report",
            "secondDuration": 178,
            "group": "group_7"
        },
        {
            "videoId": "e8MzDrjp1QQ",
            "title": "Gutfeld: Blue states are losing people quicker than CNN's primetime",
            "secondDuration": 873,
            "group": "group_7"
        },
        {
            "videoId": "DDgHjl4rgH0",
            "title": "Jim Jordan sounds off on Biden's 'America last' policy",
            "secondDuration": 403,
            "group": "group_7"
        },
        {
            "videoId": "HFnyiWcaCXs",
            "title": "Parent tells Tucker he was 'excommunicated' from school after viral letter",
            "secondDuration": 325,
            "group": "group_7"
        },
        {
            "videoId": "ZZ96YeBaUds",
            "title": "Lawrence Jones talks to citizens 'left to fend for themselves' in liberal city",
            "secondDuration": 253,
            "group": "group_7"
        },
        {
            "videoId": "-YbRNgBg9Og",
            "title": "Tucker: Most Americans aren't aware of the research",
            "secondDuration": 508,
            "group": "group_7"
        },
        {
            "videoId": "eDHf8zOAKxs",
            "title": "Here's what to expect from Biden's face-to-face meeting with Putin",
            "secondDuration": 260,
            "group": "group_7"
        },
        {
            "videoId": "NfEiINr9PnU",
            "title": "Peter Doocy grills Psaki over increased crime rates",
            "secondDuration": 216,
            "group": "group_7"
        }
    ],
    "nbPages": 7964,
    "nbResults": 79635
}