{
    "currentPage": 157,
    "pageSize": 5,
    "items": [
        {
            "videoId": "v5p7WY9nOJM",
            "title": "Why take a gap year? 6 Minute English",
            "secondDuration": 392,
            "group": "group_1"
        },
        {
            "videoId": "7s0-Hsz1r3M",
            "title": "Victoria Falls: Is Zimbabwe drying up? - Lingohack",
            "secondDuration": 226,
            "group": "group_1"
        },
        {
            "videoId": "GEiDun-fqps",
            "title": "23 sugars in one hot drink! - Watch News Review",
            "secondDuration": 703,
            "group": "group_1"
        },
        {
            "videoId": "R0QC2HTttqw",
            "title": "See vs Watch vs Look - English in a Minute",
            "secondDuration": 60,
            "group": "group_1"
        },
        {
            "videoId": "4RgPFRgkUHQ",
            "title": "What does 'dad dancing' mean?",
            "secondDuration": 173,
            "group": "group_1"
        }
    ],
    "nbPages": 566,
    "nbResults": 2826
}