{
    "currentPage": 44,
    "pageSize": 20,
    "items": [
        {
            "videoId": "NrArDMc4dtM",
            "title": "Toffee Apple-Tini",
            "secondDuration": 67,
            "group": "group_3"
        },
        {
            "videoId": "UZTGdOgV8UQ",
            "title": "Anthrax Island Bomb Shot - Tipsy Bartender",
            "secondDuration": 46,
            "group": "group_3"
        },
        {
            "videoId": "JimP3ASHOjg",
            "title": "Drainpipe Shots - Tipsy Bartender",
            "secondDuration": 62,
            "group": "group_3"
        },
        {
            "videoId": "M4JESuLUV2o",
            "title": "Armonia - Tipsy Bartender",
            "secondDuration": 214,
            "group": "group_3"
        },
        {
            "videoId": "7Cyh7bKu1A8",
            "title": "Mandarin Mojito",
            "secondDuration": 52,
            "group": "group_3"
        },
        {
            "videoId": "I_8aW1c64Ho",
            "title": "Fireball Whiskey Float",
            "secondDuration": 65,
            "group": "group_3"
        },
        {
            "videoId": "RTQaDVmIg8k",
            "title": "Blackberry Mango Margarita",
            "secondDuration": 65,
            "group": "group_3"
        },
        {
            "videoId": "gW8RvUtToZ0",
            "title": "Limoncello Spritz",
            "secondDuration": 52,
            "group": "group_3"
        },
        {
            "videoId": "jmWC90GCi4A",
            "title": "Adios MF",
            "secondDuration": 34,
            "group": "group_3"
        },
        {
            "videoId": "_tlZI5uOBUQ",
            "title": "Cashew Outside",
            "secondDuration": 188,
            "group": "group_3"
        },
        {
            "videoId": "iS-9bNg9dWE",
            "title": "Frozen Strawberry Kiwi Mojito",
            "secondDuration": 66,
            "group": "group_3"
        },
        {
            "videoId": "69IMKvj8kYs",
            "title": "Chocolate Cupcake Cocktail - Tipsy Bartender",
            "secondDuration": 59,
            "group": "group_3"
        },
        {
            "videoId": "io_ZBe8YA7Q",
            "title": "Johnny Vegas",
            "secondDuration": 45,
            "group": "group_3"
        },
        {
            "videoId": "0xVScjtInuU",
            "title": "The Surfboard",
            "secondDuration": 94,
            "group": "group_3"
        },
        {
            "videoId": "sHeNxip1H94",
            "title": "Peached Whale - Tipsy Bartender",
            "secondDuration": 47,
            "group": "group_3"
        },
        {
            "videoId": "0JfvzFsz6M4",
            "title": "Hot Toddy",
            "secondDuration": 58,
            "group": "group_3"
        },
        {
            "videoId": "sdj6pPLH8ZY",
            "title": "Strawberry Banana Pina Colada",
            "secondDuration": 64,
            "group": "group_3"
        },
        {
            "videoId": "Oi4smC9MaqM",
            "title": "Mai Tai",
            "secondDuration": 72,
            "group": "group_3"
        },
        {
            "videoId": "Bx4uQ-KoMKI",
            "title": "Trump and Stormy - Tipsy Bartender",
            "secondDuration": 64,
            "group": "group_3"
        },
        {
            "videoId": "wUPErqRjwdY",
            "title": "The Crocodile Cooler",
            "secondDuration": 37,
            "group": "group_3"
        }
    ],
    "nbPages": 82,
    "nbResults": 1640
}