{
    "currentPage": 31,
    "pageSize": 20,
    "items": [
        {
            "videoId": "Il1N322HunI",
            "title": "Ukrainian Civilians Volunteer To Train For Territorial Defense Forces",
            "secondDuration": 218,
            "group": "group_7"
        },
        {
            "videoId": "NY34dq5aOmc",
            "title": "Nightly News Full Broadcast - March 25",
            "secondDuration": 1285,
            "group": "group_7"
        },
        {
            "videoId": "wlixIqT-ZR4",
            "title": "Zelenskyy Speaks On Russian Losses Since The Invasion",
            "secondDuration": 84,
            "group": "group_7"
        },
        {
            "videoId": "oBZ0-6-_OmU",
            "title": "Lester Holt Reflects On Support For Ukraine And Its Resolve Against Russia",
            "secondDuration": 103,
            "group": "group_7"
        },
        {
            "videoId": "4hOjV2O-yjs",
            "title": "Hallie Jackson NOW - March 25 | NBC News NOW",
            "secondDuration": 3202,
            "group": "group_7"
        },
        {
            "videoId": "PlKZUzo3nUA",
            "title": "Ukraine’s Refugees Stuck In Limbo",
            "secondDuration": 149,
            "group": "group_7"
        },
        {
            "videoId": "Ab3K9a8HRt4",
            "title": "Texts Show Wife of Justice Thomas, Ginni, Urged Mark Meadows To Overturn Election Results",
            "secondDuration": 138,
            "group": "group_7"
        },
        {
            "videoId": "egahUaU_nCA",
            "title": "Exclusive Look Inside Besieged Mariupol",
            "secondDuration": 124,
            "group": "group_7"
        },
        {
            "videoId": "PEp9hogCxpw",
            "title": "Biden Travels To Poland To Survey Humanitarian Crisis",
            "secondDuration": 154,
            "group": "group_7"
        },
        {
            "videoId": "RQQOnLH0Xqc",
            "title": "Man Falls To His Death In Attempted Stunt As Teen Daughter Watches From Below",
            "secondDuration": 91,
            "group": "group_7"
        },
        {
            "videoId": "QN_HFwbpEik",
            "title": "New Jersey Mandates Teaching Asian American History In K-12",
            "secondDuration": 225,
            "group": "group_7"
        },
        {
            "videoId": "pyMWsMyNJ_A",
            "title": "Putin Claims West Is Trying To Cancel Russia",
            "secondDuration": 91,
            "group": "group_7"
        },
        {
            "videoId": "_vbBJMl6xnA",
            "title": "McCarthy On Rep. Fortenberry: 'When Someone Is Convicted, It's Time To Resign'",
            "secondDuration": 112,
            "group": "group_7"
        },
        {
            "videoId": "8_0TXbJupts",
            "title": "White House To Allow Asylum Officers To Determine If Immigrants Can Stay In U.S.",
            "secondDuration": 181,
            "group": "group_7"
        },
        {
            "videoId": "OMxGhUcXQ5Q",
            "title": "Ukrainian Lawmaker, Mayor Tour Chernihiv To Witness Destruction",
            "secondDuration": 82,
            "group": "group_7"
        },
        {
            "videoId": "5c9ej7ts4Bw",
            "title": "'No More Noble Job': School Board Polarization Pressures Teachers, Administrators",
            "secondDuration": 787,
            "group": "group_7"
        },
        {
            "videoId": "GBu2QBP3Dhk",
            "title": "Classroom Culture Wars: Who Decides? | Meet The Press Reports",
            "secondDuration": 1614,
            "group": "group_7"
        },
        {
            "videoId": "hovyLBk3MRs",
            "title": "Doctors, Politicians Pushing For Covid-Era Addiction Treatment To Be Made Permanent",
            "secondDuration": 270,
            "group": "group_7"
        },
        {
            "videoId": "JphS_McK6uU",
            "title": "Ukrainian Hackers Waging Shadow War To Expose Russian Secrets",
            "secondDuration": 249,
            "group": "group_7"
        },
        {
            "videoId": "-xkRaHluMXc",
            "title": "What Kanye West Can Teach Us About Bipolar Disorder, Black Mental Health",
            "secondDuration": 225,
            "group": "group_7"
        }
    ],
    "nbPages": 1842,
    "nbResults": 36826
}