{
    "currentPage": 439,
    "pageSize": 10,
    "items": [
        {
            "videoId": "xBubQ4sd8xc",
            "title": "Largest iceberg in the world moves towards South Georgia Island",
            "secondDuration": 66,
            "group": "group_7"
        },
        {
            "videoId": "MT0pnY3FpG0",
            "title": "Rudy Giuliani doubles down on US Election 2020 Georgia vote fraud claims",
            "secondDuration": 282,
            "group": "group_7"
        },
        {
            "videoId": "8V_qu14ip9Q",
            "title": "Boris Johnson pays tribute to Barbara Windsor",
            "secondDuration": 32,
            "group": "group_7"
        },
        {
            "videoId": "O0r_GZIH66g",
            "title": "Angry giraffe chases tourists and overtakes car to block their path",
            "secondDuration": 106,
            "group": "group_7"
        },
        {
            "videoId": "hLNkLhW-FfA",
            "title": "Police looking for suspect find him hiding right behind them",
            "secondDuration": 30,
            "group": "group_7"
        },
        {
            "videoId": "mNK_ZUsuMAg",
            "title": "Skydiver swings and jumps off a hot air balloon - DailyMail TV",
            "secondDuration": 48,
            "group": "group_7"
        },
        {
            "videoId": "MZ2bKRlOmZw",
            "title": "Mom plans to get teen son nose job for Christmas - DailyMail TV",
            "secondDuration": 111,
            "group": "group_7"
        },
        {
            "videoId": "tIXto-tUdcE",
            "title": "Banksy confirms mural of sneezing pensioner is his work",
            "secondDuration": 276,
            "group": "group_7"
        },
        {
            "videoId": "lBUtOu9E_ZU",
            "title": "Florida police release bodycam of raid on COVID whistleblower's home",
            "secondDuration": 243,
            "group": "group_7"
        },
        {
            "videoId": "bsqvd5T0U98",
            "title": "Barbara Windsor shows The Queen around the set of EastEnders in 2001",
            "secondDuration": 91,
            "group": "group_7"
        }
    ],
    "nbPages": 710,
    "nbResults": 7096
}