{
    "currentPage": 13194,
    "pageSize": 5,
    "items": [
        {
            "videoId": "hV4XmwNKsu4",
            "title": "Beware pricey, perhaps unneeded heart procedure",
            "secondDuration": 214,
            "group": "group_7"
        },
        {
            "videoId": "Ex4L0NFYvYI",
            "title": "Giffords aide: She was thrilled about House return",
            "secondDuration": 146,
            "group": "group_7"
        },
        {
            "videoId": "TZHHZI1ZcdI",
            "title": "Video shows another girl taken by Dugard kidnappers",
            "secondDuration": 154,
            "group": "group_7"
        },
        {
            "videoId": "GhAwj0NtxQ4",
            "title": "Source of tainted turkey meat still unknown",
            "secondDuration": 26,
            "group": "group_7"
        },
        {
            "videoId": "_tS_hmUhUqo",
            "title": "Mubarak in Cairo courtroom on stretcher",
            "secondDuration": 153,
            "group": "group_7"
        }
    ],
    "nbPages": 16908,
    "nbResults": 84536
}