{
    "currentPage": 16054,
    "pageSize": 5,
    "items": [
        {
            "videoId": "vVktT36gtjs",
            "title": "The Showbuzz: Crazy Heart",
            "secondDuration": 115,
            "group": "group_7"
        },
        {
            "videoId": "36_wM-A67Yk",
            "title": "Evening News Online, 12.18.09",
            "secondDuration": 1231,
            "group": "group_7"
        },
        {
            "videoId": "tjpKqioEqjc",
            "title": "Connecting Lives Worldwide",
            "secondDuration": 158,
            "group": "group_7"
        },
        {
            "videoId": "aM9cwv5-3Vo",
            "title": "GOP Stalls Healthcare Bill",
            "secondDuration": 204,
            "group": "group_7"
        },
        {
            "videoId": "gRBY8b1pmWs",
            "title": "Obama's \"Breakthrough\"",
            "secondDuration": 147,
            "group": "group_7"
        }
    ],
    "nbPages": 16908,
    "nbResults": 84536
}