{
    "currentPage": 3593,
    "pageSize": 5,
    "items": [
        {
            "videoId": "sX6uYiJuPEk",
            "title": "Black transgender woman found burned to death in Florida",
            "secondDuration": 93,
            "group": "group_7"
        },
        {
            "videoId": "D1vnMh8zqpo",
            "title": "\"Stand with Parkland\" founder responds to Andrew Pollack's criticisms",
            "secondDuration": 407,
            "group": "group_7"
        },
        {
            "videoId": "hZfxvEqNe5E",
            "title": "Felicity Huffman sentenced to 14 days in jail",
            "secondDuration": 118,
            "group": "group_7"
        },
        {
            "videoId": "PEy3sRY7xvw",
            "title": "CBS News poll reveals Democrats' first and second-choice candidates",
            "secondDuration": 259,
            "group": "group_7"
        },
        {
            "videoId": "6VerftAJsh8",
            "title": "Biden defends health care stance after being accused of flip-flopping at debate",
            "secondDuration": 325,
            "group": "group_7"
        }
    ],
    "nbPages": 16908,
    "nbResults": 84536
}