{
    "currentPage": 1339,
    "pageSize": 10,
    "items": [
        {
            "videoId": "hlYLz3Q564w",
            "title": "Trump Dividing The Nation BIGLY",
            "secondDuration": 359,
            "group": "group_7"
        },
        {
            "videoId": "zA7VyrpnBho",
            "title": "POLL: Few Voters Impressed With Trump's Biggest Accomplishment",
            "secondDuration": 173,
            "group": "group_7"
        },
        {
            "videoId": "3tOrspNYUbQ",
            "title": "District Attorney Making GROUNDBREAKING Justice Reform",
            "secondDuration": 299,
            "group": "group_7"
        },
        {
            "videoId": "Q9xZcicGsW0",
            "title": "Russia Is Far From the Only Country Influencing U.S. Elections",
            "secondDuration": 392,
            "group": "group_7"
        },
        {
            "videoId": "LipcnjaSkis",
            "title": "INSPIRATIONAL Speech From California's Next Senator Alison Hartson",
            "secondDuration": 873,
            "group": "group_7"
        },
        {
            "videoId": "rTuaE2oZViY",
            "title": "The NRA Isn't the True Villain Behind Gun Violence",
            "secondDuration": 254,
            "group": "group_7"
        },
        {
            "videoId": "hb4jLIF7_cM",
            "title": "Chiquita Profits BIG TIME Off Terror",
            "secondDuration": 372,
            "group": "group_7"
        },
        {
            "videoId": "mFu3-10Csh0",
            "title": "The Next Congressman from NY-21! Dylan Ratigan Interview with Cenk Uygur",
            "secondDuration": 1856,
            "group": "group_7"
        },
        {
            "videoId": "XU08L4CMmfI",
            "title": "Male Circumcision OUTLAWED In Iceland",
            "secondDuration": 503,
            "group": "group_7"
        },
        {
            "videoId": "jTgrOmerd8o",
            "title": "STUDY: Emotional Support Pets Aren't Real",
            "secondDuration": 136,
            "group": "group_7"
        }
    ],
    "nbPages": 2729,
    "nbResults": 27290
}