{
    "currentPage": 1599,
    "pageSize": 20,
    "items": [
        {
            "videoId": "7rpr0bDNtxA",
            "title": "Πόσοι άνθρωποι μπορούν να κρυφτούν μέσα μας ? | Nikolaos Gkouvas | TEDxUniversityoftheAegean",
            "secondDuration": 1075,
            "group": "group_14"
        },
        {
            "videoId": "yMrfNyv-rf0",
            "title": "Ideas are within us, we just need to ask the right questions. | VJ Clince Verghese | TEDxYouth@AUS",
            "secondDuration": 1109,
            "group": "group_14"
        },
        {
            "videoId": "xrk7A-ecFO0",
            "title": "Beyond Crisis: What's Possible for Masculinity | Michael Kramp | TEDxOronocoBayPark",
            "secondDuration": 817,
            "group": "group_14"
        },
        {
            "videoId": "ZVSznnuPJF0",
            "title": "Life after domestic violence. | Oona umutoni | TEDxKids@Nyarugenge",
            "secondDuration": 330,
            "group": "group_14"
        },
        {
            "videoId": "kC3vmTaaQN8",
            "title": "Change from a child | Nzobe Nilita Imani | TEDxKids@Nyarugenge",
            "secondDuration": 344,
            "group": "group_14"
        },
        {
            "videoId": "1boFO5UV-YQ",
            "title": "Είμαι τρανς / I am Trans | Danai Theodoridou | TEDxUniversityoftheAegean",
            "secondDuration": 898,
            "group": "group_14"
        },
        {
            "videoId": "BpQyWOSYgbo",
            "title": "Εσύ, είσαι σίγουρος ότι παραμένεις ίδιος? | Danai Barka | TEDxUniversityoftheAegean",
            "secondDuration": 1263,
            "group": "group_14"
        },
        {
            "videoId": "BgU4u2NB2UE",
            "title": "Empowering disabled children. | Bosco Nyirikwizerwa | TEDxKids@Nyarugenge",
            "secondDuration": 511,
            "group": "group_14"
        },
        {
            "videoId": "4z0DqpdUdRE",
            "title": "Be the change you want to see. | Mucunguzi Izere Joselyne | TEDxKids@Nyarugenge",
            "secondDuration": 435,
            "group": "group_14"
        },
        {
            "videoId": "k7Bh6gow_a0",
            "title": "Le futur, c'est la Réalité Étendue pour tous | Marie-Parisius D HOUESSOU | TEDxGanhito",
            "secondDuration": 691,
            "group": "group_14"
        },
        {
            "videoId": "Er4Q1b6maSs",
            "title": "The Straw Movement: It’s Not Just About the Straws | Jagger Vetter | TEDxMasonHighSchool",
            "secondDuration": 918,
            "group": "group_14"
        },
        {
            "videoId": "sceQOCMdUws",
            "title": "Πως Ένας Πυρήνας του Εγκεφάλου με Ανακάλυψε | George Paxinos | TEDxUniversityoftheAegean",
            "secondDuration": 1022,
            "group": "group_14"
        },
        {
            "videoId": "LLFFEMvzxVE",
            "title": "Забота о планете: от науки к конкретным действиям | Кристина Роппельт | TEDxSadovoeRingSalon",
            "secondDuration": 1077,
            "group": "group_14"
        },
        {
            "videoId": "JwfQBOV2u-M",
            "title": "Экология как наука | Юлия Кузнецова | TEDxSadovoeRingSalon",
            "secondDuration": 1303,
            "group": "group_14"
        },
        {
            "videoId": "7hRmVqNsBBI",
            "title": "Проблема экологии в том, что мы не видим проблему | Алексей Молчанов | TEDxSadovoeRingSalon",
            "secondDuration": 680,
            "group": "group_14"
        },
        {
            "videoId": "B7fFRS6aDYo",
            "title": "Dance Performance | Maria Trika & Tonia Kehagia | TEDxUniversityoftheAegean",
            "secondDuration": 903,
            "group": "group_14"
        },
        {
            "videoId": "sDboSh_kPhs",
            "title": "Big lies of small lives. | Rutangwa Sugira Lorie | TEDxKids@Nyarugenge",
            "secondDuration": 467,
            "group": "group_14"
        },
        {
            "videoId": "r-u9hY6qQzs",
            "title": "How to be a successful driver guide | Nadia Badiee | TEDxYouth@ZandSt",
            "secondDuration": 546,
            "group": "group_14"
        },
        {
            "videoId": "PghujV1LAeY",
            "title": "Μπροστά στο τέλος. Υπάρχει \"ευθάνατος\" θάνατος; | Georgios Kranidiotis | TEDxUniversityoftheAegean",
            "secondDuration": 1142,
            "group": "group_14"
        },
        {
            "videoId": "-oJPcnpXONA",
            "title": "Mind the Gap - Being Gender Responsive in Criminal Justice | Kim Bogucki | TEDxJIBC",
            "secondDuration": 728,
            "group": "group_14"
        }
    ],
    "nbPages": 1732,
    "nbResults": 34631
}