{
    "currentPage": 463,
    "pageSize": 10,
    "items": [
        {
            "videoId": "5uZlj0CrIJk",
            "title": "CGI VFX Matte Painting & Compositing Showreels : by Chirag Tripathy",
            "secondDuration": 165,
            "group": "group_11"
        },
        {
            "videoId": "5ZCsUbRydBU",
            "title": "CGI VFX Blender Short: \"Tears of Steel\" - by Blender Animation Studio | TheCGBros",
            "secondDuration": 734,
            "group": "group_11"
        },
        {
            "videoId": "hZhiwppXdJ8",
            "title": "CGI VFX Behind The Scenes : \"Ted\" Using the Mocap system MVN | TheCGBros",
            "secondDuration": 111,
            "group": "group_11"
        },
        {
            "videoId": "OjY1KP2xKP0",
            "title": "CGI Animated Spot : \"Breakdance\" for - Red Bull",
            "secondDuration": 39,
            "group": "group_11"
        },
        {
            "videoId": "zQu4D3LeVhE",
            "title": "CGI Motion Graphics Spot : \"Econews Ident\" by Anthimos Xenos",
            "secondDuration": 35,
            "group": "group_11"
        },
        {
            "videoId": "z0iNMPmiihk",
            "title": "CGI 3D Motion Graphics : \"Monster Jam\"",
            "secondDuration": 46,
            "group": "group_11"
        },
        {
            "videoId": "NJZgRENtk7A",
            "title": "CGI VFX Spot : \"Mitsubishi Estrada\" by Tribbo Post",
            "secondDuration": 65,
            "group": "group_11"
        },
        {
            "videoId": "imPwJ_AsVk8",
            "title": "CGI VFX Breakdowns :  \"Games of Thrones\" by Bluebolt VFX | TheCGBros",
            "secondDuration": 207,
            "group": "group_11"
        },
        {
            "videoId": "xlHueZKVgSI",
            "title": "CGI VFX Breakdowns 1080 : \"Puhdistus Purge\" by Fake Graphics",
            "secondDuration": 149,
            "group": "group_11"
        },
        {
            "videoId": "qy0U_74OGa0",
            "title": "CGI 3D Cinematic Game Trailer: \"The Witcher 2 - Assasins Of Kings\" - by Platige Image",
            "secondDuration": 253,
            "group": "group_11"
        }
    ],
    "nbPages": 479,
    "nbResults": 4790
}