{
    "currentPage": 811,
    "pageSize": 5,
    "items": [
        {
            "videoId": "A78ZPf9Fw1w",
            "title": "Rum Julep Recipe | Summer Drinks | The New York Times",
            "secondDuration": 62,
            "group": "group_7"
        },
        {
            "videoId": "HfAzfpSnoYM",
            "title": "Rum and Tonic Recipe | Summer Drinks | The New York Times",
            "secondDuration": 36,
            "group": "group_7"
        },
        {
            "videoId": "uom7ruYea2s",
            "title": "Honey Bee Recipe | Summer Drinks | The New York Times",
            "secondDuration": 67,
            "group": "group_7"
        },
        {
            "videoId": "RPyt3rAuhh8",
            "title": "Fashion in Eastern Congo | Intersection | The New York Times",
            "secondDuration": 171,
            "group": "group_7"
        },
        {
            "videoId": "rKu9IjoYdpM",
            "title": "Belmont Stakes Preview 2014 | The New York Times",
            "secondDuration": 166,
            "group": "group_7"
        }
    ],
    "nbPages": 1998,
    "nbResults": 9990
}