{
    "currentPage": 694,
    "pageSize": 5,
    "items": [
        {
            "videoId": "yKyo8_u8UFo",
            "title": "CDC Panel Recommends Pfizer, Moderna Boosters For All Adults",
            "secondDuration": 194,
            "group": "group_7"
        },
        {
            "videoId": "P-h-euwYdOU",
            "title": "'Turkey Is Infrastructure': Biden Pardons National Thanksgiving Turkey",
            "secondDuration": 106,
            "group": "group_7"
        },
        {
            "videoId": "iDR_IofndLo",
            "title": "LIVE: Kyle Rittenhouse Acquitted On All Charges | NBC News",
            "secondDuration": 1211,
            "group": "group_7"
        },
        {
            "videoId": "3RYg3pXXLOM",
            "title": "Analyzing Jury's Decision To Acquit Kyle Rittenhouse On All Charges",
            "secondDuration": 322,
            "group": "group_7"
        },
        {
            "videoId": "990E-T3wEaE",
            "title": "WATCH: Kyle Rittenhouse Breaks Down In Tears As Jury Acquits On All Charges",
            "secondDuration": 141,
            "group": "group_7"
        }
    ],
    "nbPages": 7366,
    "nbResults": 36826
}